CONTRIBUTING.md
LICENSE
MANIFEST.in
README.md
settings.ini
setup.py
parquet_performance/__init__.py
parquet_performance/_nbdev.py
parquet_performance/core.py
parquet_performance.egg-info/PKG-INFO
parquet_performance.egg-info/SOURCES.txt
parquet_performance.egg-info/dependency_links.txt
parquet_performance.egg-info/entry_points.txt
parquet_performance.egg-info/not-zip-safe
parquet_performance.egg-info/top_level.txt