Metadata-Version: 2.1
Name: parquet-performance
Version: 0.0.2
Summary: Performance of parquet files using pandas
Home-page: https://github.com/gavinln/parquet_performance/tree/master/
Author: Gavin Noronha
Author-email: gavinln@hotmail.com
License: Apache Software License 2.0
Keywords: parquet pandas performance
Platform: UNKNOWN
Classifier: Development Status :: 3 - Alpha
Classifier: Intended Audience :: Developers
Classifier: License :: OSI Approved :: Apache Software License
Classifier: Natural Language :: English
Classifier: Programming Language :: Python :: 3.6
Classifier: Programming Language :: Python :: 3.7
Classifier: Programming Language :: Python :: 3.8
Requires-Python: >=3.6
